shadowhash/__init__.py
shadowhash/__main__.py
shadowhash/version.py
shadowhash-0.0.1.dist-info/LICENSE
shadowhash-0.0.1.dist-info/METADATA
shadowhash-0.0.1.dist-info/WHEEL
shadowhash-0.0.1.dist-info/entry_points.txt
shadowhash-0.0.1.dist-info/top_level.txt
shadowhash-0.0.1.dist-info/RECORD
