Metadata-Version: 2.1
Name: shadowhash
Version: 0.0.1
Summary: Generate /etc/shadow crypt hashes
Home-page: https://gitlab.com/zer1t0/shadowhash
Author: Eloy Perez
Author-email: zer1t0ps@protonmail.com
Classifier: Programming Language :: Python :: 3
Classifier: License :: OSI Approved :: GNU General Public License v3 (GPLv3)
License-File: LICENSE
Requires-Dist: passlib
Requires-Dist: bcrypt
Requires-Dist: pyescrypt
